LICENSE
README.md
setup.py
src/ccds_maskdetection.egg-info/PKG-INFO
src/ccds_maskdetection.egg-info/SOURCES.txt
src/ccds_maskdetection.egg-info/dependency_links.txt
src/ccds_maskdetection.egg-info/top_level.txt
src/data/__init__.py
src/data/make_dataset.py
src/features/__init__.py
src/features/build_features.py
src/models/__init__.py
src/models/predict_model.py
src/models/train_model.py
src/visualization/__init__.py
src/visualization/visualize.py